dcmReader/__init__.py
dcmReader/__main__.py
dcmReader/dcm_characteristic_line.py
dcmReader/dcm_characteristic_map.py
dcmReader/dcm_distribution.py
dcmReader/dcm_fixed_characteristic_line.py
dcmReader/dcm_fixed_characteristic_map.py
dcmReader/dcm_function.py
dcmReader/dcm_group_characteristic_line.py
dcmReader/dcm_group_characteristic_map.py
dcmReader/dcm_parameter.py
dcmReader/dcm_parameter_block.py
dcmReader/dcm_reader.py
dcmreader-0.5.0.dist-info/licenses/LICENSE
dcmreader-0.5.0.dist-info/METADATA
dcmreader-0.5.0.dist-info/WHEEL
dcmreader-0.5.0.dist-info/top_level.txt
dcmreader-0.5.0.dist-info/RECORD
