Metadata-Version: 2.4
Name: dcmReader
Version: 0.5.0
Summary: Parser for the DCM (Data Conservation format) format used by e.g. Vector, ETAS,...
Home-page: https://github.com/dkuschmierz/dcmReader
Author: Dominic Kuschmierz
Author-email: dominic@kuschmierz.org
Project-URL: Bug Tracker, https://github.com/dkuschmierz/dcmReader/issues
Classifier: Programming Language :: Python :: 3
Classifier: License :: OSI Approved :: MIT License
Classifier: Operating System :: OS Independent
Classifier: Topic :: Scientific/Engineering :: Information Analysis
Requires-Python: >=3.6
License-File: LICENSE
Dynamic: author
Dynamic: author-email
Dynamic: classifier
Dynamic: description
Dynamic: description-content-type
Dynamic: home-page
Dynamic: license-file
Dynamic: project-url
Dynamic: requires-python
Dynamic: summary
